conan_exoplanet.libs/libquadmath-96973f99.so.0.0.0
conan_exoplanet.libs/libgfortran-040039e1.so.5.0.0
conan_exoplanet-3.3.12.dist-info/RECORD
conan_exoplanet-3.3.12.dist-info/LICENSE
conan_exoplanet-3.3.12.dist-info/METADATA
conan_exoplanet-3.3.12.dist-info/top_level.txt
conan_exoplanet-3.3.12.dist-info/WHEEL
CONAN/occultnl.cpython-310-x86_64-linux-gnu.so
CONAN/outputs.py
CONAN/euler_fit_script.py
CONAN/logprob_multi.py
CONAN/get_files.py
CONAN/_classes.py
CONAN/utils.py
CONAN/occultquad_pya.py
CONAN/VERSION.py
CONAN/priors.py
CONAN/misc.py
CONAN/plotting.py
CONAN/geepee.py
CONAN/models.py
CONAN/funcs.py
CONAN/basecoeff_setup.py
CONAN/occultquad.cpython-310-x86_64-linux-gnu.so
CONAN/conf.py
CONAN/__init__.py
CONAN/fit_data.py
