Metadata-Version: 2.1
Name: conan-exoplanet
Version: 3.3.12
Summary: COde for exoplaNet ANalysis
Author-email: Babatunde Akinsanmi <tunde.akinsanmi@unige.ch>, Monika Lendl <monika.lendl@unige.ch>
Maintainer-email: Babatunde Akinsanmi <tunde.akinsanmi@unige.ch>
Project-URL: Homepage, https://github.com/titans-ge/CONAN
Project-URL: Repository, https://github.com/titans-ge/CONAN
Project-URL: Documentation, https://conan-exoplanet.readthedocs.io/en/latest/
Project-URL: Changelog, https://github.com/titans-ge/CONAN/blob/main/change_log.rst
Project-URL: Issues, https://github.com/titans-ge/CONAN/issues
Classifier: Programming Language :: Python :: 3.10
Classifier: Programming Language :: Python :: 3.11
Classifier: License :: OSI Approved :: MIT License
Classifier: Operating System :: OS Independent
Requires-Python: >=3.10
License-File: LICENSE
Requires-Dist: numpy
Requires-Dist: chainconsumer==1.1.2
Requires-Dist: scipy
Requires-Dist: pandas
Requires-Dist: lmfit
Requires-Dist: dynesty
Requires-Dist: astropy
Requires-Dist: astroquery
Requires-Dist: celerite
Requires-Dist: corner
Requires-Dist: lightkurve
Requires-Dist: dill
Requires-Dist: dace-query
Requires-Dist: matplotlib
Requires-Dist: emcee
Requires-Dist: george
Requires-Dist: ldtk==1.7.0
Requires-Dist: tqdm
Requires-Dist: spleaf
Requires-Dist: numba
Requires-Dist: h5py
Requires-Dist: PyYAML>=6.0
Provides-Extra: test
Requires-Dist: pytest; extra == "test"
Requires-Dist: batman-package; extra == "test"
Requires-Dist: radvel; extra == "test"
Requires-Dist: h5py; extra == "test"
